{
  "$schema": "https://design-tokens.github.io/community-group/format/",
  "$description": "BAZILAR Design System v2.5 — Quiet Luxury Tupiniquim",
  "$version": "2.5.0",
  "$generated": "2026-03-13T00:00:00.000Z",
  "$note": "Fonte de verdade: src/styles/tokens.css v2.5. Paleta v2.3 removida.",

  "color": {

    "$comment-surfaces": "Superfícies — light mode",
    "--color-bg":      { "$value": "#F6F3ED", "$type": "color", "$description": "Fundo principal · areia quente" },
    "--color-surface": { "$value": "#FDFCF9", "$type": "color", "$description": "Superfície elevada · cards" },
    "--color-subtle":  { "$value": "#EDE9E0", "$type": "color", "$description": "Inputs, rows alternados" },

    "$comment-text": "Texto — light mode",
    "--color-text":           { "$value": "#1E1B15", "$type": "color", "$description": "Primário · contraste 14.8:1 AAA" },
    "--color-text-secondary": { "$value": "#4C4538", "$type": "color", "$description": "Secundário · 7.2:1 AAA" },
    "--color-text-muted":     { "$value": "#7C7264", "$type": "color", "$description": "Mudo · 4.56:1 AA" },
    "--color-text-dim":       { "$value": "#ACA090", "$type": "color", "$description": "Decorativo · 2.8:1 — não usar em texto" },

    "$comment-gold": "Ouro matte — light mode",
    "--color-gold":        { "$value": "#967438", "$type": "color", "$description": "Acento principal · 4.52:1 AA sobre bg" },
    "--color-gold-light":  { "$value": "#B8924C", "$type": "color", "$description": "Hover" },
    "--color-gold-bg":     { "$value": "rgba(150,116,56,0.08)", "$type": "color", "$description": "Fundo suave dourado" },
    "--color-gold-border": { "$value": "rgba(150,116,56,0.20)", "$type": "color", "$description": "Bordas douradas" },

    "$comment-feedback": "Feedback semântico",
    "--color-feedback-success": { "$value": "#2E7D52", "$type": "color" },
    "--color-feedback-error":   { "$value": "#8C3030", "$type": "color" },
    "--color-warning":          { "$value": "#C45A20", "$type": "color" },

    "$comment-surfaces-dark": "Superfícies — dark mode",
    "--color-bg-dark":      { "$value": "#0F0E0A", "$type": "color" },
    "--color-surface-dark": { "$value": "#1A1914", "$type": "color" },
    "--color-subtle-dark":  { "$value": "#222018", "$type": "color" },

    "$comment-text-dark": "Texto — dark mode",
    "--color-text-dark":           { "$value": "#F2EEE4", "$type": "color" },
    "--color-text-secondary-dark": { "$value": "#C4BAA6", "$type": "color" },
    "--color-text-muted-dark":     { "$value": "#867C6A", "$type": "color" },
    "--color-text-dim-dark":       { "$value": "#524C40", "$type": "color" },

    "$comment-gold-dark": "Ouro matte — dark mode",
    "--color-gold-dark":        { "$value": "#C09A4A", "$type": "color", "$description": "7.1:1 AAA sobre #0F0E0A" },
    "--color-gold-light-dark":  { "$value": "#D4B060", "$type": "color" },
    "--color-gold-bg-dark":     { "$value": "rgba(192,154,74,0.09)", "$type": "color" },
    "--color-gold-border-dark": { "$value": "rgba(192,154,74,0.22)", "$type": "color" },

    "$comment-wuxing": "Wu Xing 五行 — light mode · lápis-lazúli · esmeralda · cinábrio · âmbar · prata fria",
    "--element-water-dark":  { "$value": "#1C3A72", "$type": "color", "$description": "水 Água escuro" },
    "--element-water-base":  { "$value": "#2652A8", "$type": "color", "$description": "水 Água base" },
    "--element-water-light": { "$value": "#B8CCF0", "$type": "color", "$description": "水 Água claro" },
    "--element-wood-dark":   { "$value": "#0B5233", "$type": "color", "$description": "木 Madeira escuro" },
    "--element-wood-base":   { "$value": "#147A48", "$type": "color", "$description": "木 Madeira base" },
    "--element-wood-light":  { "$value": "#A8DBBF", "$type": "color", "$description": "木 Madeira claro" },
    "--element-fire-dark":   { "$value": "#8C0A12", "$type": "color", "$description": "火 Fogo escuro" },
    "--element-fire-base":   { "$value": "#D3232E", "$type": "color", "$description": "火 Fogo base" },
    "--element-fire-light":  { "$value": "#F5BBBF", "$type": "color", "$description": "火 Fogo claro" },
    "--element-earth-dark":  { "$value": "#7A4C08", "$type": "color", "$description": "土 Terra escuro" },
    "--element-earth-base":  { "$value": "#B87C14", "$type": "color", "$description": "土 Terra base" },
    "--element-earth-light": { "$value": "#F0E0A0", "$type": "color", "$description": "土 Terra claro" },
    "--element-metal-dark":  { "$value": "#383838", "$type": "color", "$description": "金 Metal escuro" },
    "--element-metal-base":  { "$value": "#848484", "$type": "color", "$description": "金 Metal base" },
    "--element-metal-light": { "$value": "#E0E0E0", "$type": "color", "$description": "金 Metal claro" },
    "--element-badge-text":  { "$value": "rgba(255,255,255,0.66)", "$type": "color", "$description": "Texto em badge de elemento" },

    "$comment-wuxing-dark": "Wu Xing — dark mode",
    "--element-water-dark-dm":  { "$value": "#7AA0E0", "$type": "color" },
    "--element-water-base-dm":  { "$value": "#3060C0", "$type": "color" },
    "--element-water-light-dm": { "$value": "#0A1830", "$type": "color" },
    "--element-wood-dark-dm":   { "$value": "#50C880", "$type": "color" },
    "--element-wood-base-dm":   { "$value": "#0E6038", "$type": "color" },
    "--element-wood-light-dm":  { "$value": "#061A10", "$type": "color" },
    "--element-fire-dark-dm":   { "$value": "#F05060", "$type": "color" },
    "--element-fire-base-dm":   { "$value": "#A81820", "$type": "color" },
    "--element-fire-light-dm":  { "$value": "#300810", "$type": "color" },
    "--element-earth-dark-dm":  { "$value": "#E8B020", "$type": "color" },
    "--element-earth-base-dm":  { "$value": "#A07808", "$type": "color" },
    "--element-earth-light-dm": { "$value": "#1E1400", "$type": "color" },
    "--element-metal-dark-dm":  { "$value": "#C8C8C8", "$type": "color" },
    "--element-metal-base-dm":  { "$value": "#848484", "$type": "color" },
    "--element-metal-light-dm": { "$value": "#1C1C1C", "$type": "color" }
  },

  "typography": {
    "$comment-families": "Famílias — DS v2.5",
    "--font-heading":  { "$value": "'Lora', 'Noto Serif SC', serif",     "$type": "fontFamily", "$description": "Display, interpretações" },
    "--font-body":     { "$value": "'Noto Sans', system-ui, sans-serif", "$type": "fontFamily", "$description": "Interface, labels" },
    "--font-mono":     { "$value": "'JetBrains Mono', monospace",        "$type": "fontFamily", "$description": "Dados runtime — NUNCA em itálico" },
    "--font-chinese":  { "$value": "'Noto Serif SC', serif",             "$type": "fontFamily", "$description": "CJK — NUNCA em itálico" },

    "$comment-scale": "Escala tipográfica — razão 1.333 · base 16px · DECISÃO: 1.25 mantida em implementação (ver DS_v2.3_SPEC.md §4.2)",
    "--text-ctx":    { "$value": "0.563rem", "$type": "dimension", "$description": "9.0px — contextual: pil-head, stems, luck-age" },
    "--text-label":  { "$value": "0.750rem", "$type": "dimension", "$description": "12.0px — label: term-dot, star-name, elem-name" },
    "--text-pinyin": { "$value": "0.6875rem","$type": "dimension", "$description": "11.0px — fixo, Noto Sans, sem itálico" },
    "--text-base":   { "$value": "1.000rem", "$type": "dimension", "$description": "16.0px — body, inputs, panel-title" },
    "--text-dest":   { "$value": "1.333rem", "$type": "dimension", "$description": "21.3px — rst-val, destaque" },
    "--text-cjk":    { "$value": "1.776rem", "$type": "dimension", "$description": "28.4px — luck-chars, CJK médio" },
    "--text-glyph":  { "$value": "3.157rem", "$type": "dimension", "$description": "50.5px — bazi-pillar__char" },

    "$comment-leading": "Line-height",
    "--leading-tight":  { "$value": "1.2", "$type": "number" },
    "--leading-snug":   { "$value": "1.4", "$type": "number" },
    "--leading-normal": { "$value": "1.6", "$type": "number" },
    "--leading-loose":  { "$value": "1.8", "$type": "number" },

    "$comment-tracking": "Letter-spacing",
    "--tracking-normal":  { "$value": "0",      "$type": "dimension" },
    "--tracking-wide":    { "$value": "0.04em",  "$type": "dimension" },
    "--tracking-wider":   { "$value": "0.08em",  "$type": "dimension" },
    "--tracking-widest":  { "$value": "0.18em",  "$type": "dimension" },
    "--tracking-ultra":   { "$value": "0.20em",  "$type": "dimension" }
  },

  "spacing": {
    "$comment": "Base 8px — DS v2.5",
    "--space-1":  { "$value": "8px",  "$type": "dimension" },
    "--space-2":  { "$value": "16px", "$type": "dimension" },
    "--space-3":  { "$value": "24px", "$type": "dimension" },
    "--space-4":  { "$value": "32px", "$type": "dimension" },
    "--space-5":  { "$value": "40px", "$type": "dimension" },
    "--space-6":  { "$value": "48px", "$type": "dimension" },
    "--space-8":  { "$value": "64px", "$type": "dimension" },
    "--space-10": { "$value": "80px", "$type": "dimension" },
    "--space-12": { "$value": "96px", "$type": "dimension" },

    "$comment-containers": "Containers",
    "--content-max":   { "$value": "720px", "$type": "dimension" },
    "--container-sm":  { "$value": "480px", "$type": "dimension" },
    "--container-md":  { "$value": "720px", "$type": "dimension" },
    "--container-lg":  { "$value": "960px", "$type": "dimension" },
    "--pillar-min-w":  { "$value": "80px",  "$type": "dimension", "$description": "REQ-05" },
    "--pillar-min-h":  { "$value": "120px", "$type": "dimension", "$description": "REQ-05" }
  },

  "border": {
    "--radius-sm":   { "$value": "4px",    "$type": "dimension" },
    "--radius-md":   { "$value": "8px",    "$type": "dimension" },
    "--radius-lg":   { "$value": "12px",   "$type": "dimension" },
    "--radius-xl":   { "$value": "16px",   "$type": "dimension" },
    "--radius-full": { "$value": "9999px", "$type": "dimension" },
    "--border-thin":   { "$value": "1px", "$type": "dimension" },
    "--border-medium": { "$value": "2px", "$type": "dimension" }
  },

  "shadow": {
    "--shadow-sm":   { "$value": "0 1px 3px rgba(30,27,21,.07)",  "$type": "shadow" },
    "--shadow-md":   { "$value": "0 4px 18px rgba(30,27,21,.09)", "$type": "shadow" },
    "--shadow-gold": { "$value": "0 4px 18px rgba(150,116,56,.20)", "$type": "shadow" },
    "--focus-ring":  { "$value": "0 0 0 3px rgba(150,116,56,.20)", "$type": "shadow" },
    "--shadow-sm-dark":   { "$value": "0 1px 4px rgba(0,0,0,.35)",  "$type": "shadow" },
    "--shadow-md-dark":   { "$value": "0 4px 22px rgba(0,0,0,.45)", "$type": "shadow" },
    "--shadow-gold-dark": { "$value": "0 4px 18px rgba(192,154,74,.22)", "$type": "shadow" },
    "--focus-ring-dark":  { "$value": "0 0 0 3px rgba(192,154,74,.22)", "$type": "shadow" }
  },

  "motion": {
    "--ease":            { "$value": "cubic-bezier(.25,.1,.25,1)",  "$type": "cubicBezier" },
    "--ease-standard":   { "$value": "cubic-bezier(.25,.1,.25,1)",  "$type": "cubicBezier" },
    "--ease-decelerate": { "$value": "cubic-bezier(0,.0,.2,1)",     "$type": "cubicBezier" },
    "--ease-accelerate": { "$value": "cubic-bezier(.4,0,1,1)",      "$type": "cubicBezier" },
    "--ease-out":        { "$value": "cubic-bezier(.4,0,.2,1)",     "$type": "cubicBezier" },
    "--duration-fast":    { "$value": "200ms", "$type": "duration" },
    "--duration-normal":  { "$value": "350ms", "$type": "duration" },
    "--duration-slow":    { "$value": "500ms", "$type": "duration" },
    "--duration-stagger": { "$value": "80ms",  "$type": "duration", "$description": "Delay entre pilares na entrada" },
    "--enter-y":          { "$value": "14px",  "$type": "dimension", "$description": "translateY inicial em pillar-enter" }
  },

  "surface": {
    "--surface-glass":      { "$value": "rgba(246,243,237,0.82)", "$type": "color", "$description": "Topbar light" },
    "--surface-glass-dark": { "$value": "rgba(15,14,10,0.88)",    "$type": "color", "$description": "Topbar dark" }
  }
}
